oktoblas-1.0.9.post1.dist-info/METADATA
oktoblas-1.0.9.post1.dist-info/WHEEL
oktoblas-1.0.9.post1.dist-info/licenses/LICENSE.txt
oktoblas/__init__.py
oktoblas/__pycache__/__init__.cpython-310.pyc
oktoblas/__pycache__/__init__.cpython-314.pyc
oktoblas/_oktoblas.cp310-win_amd64.pyd
oktoblas-1.0.9.post1.dist-info/RECORD
