Metadata-Version: 2.4
Name: oktoblas
Version: 1.0.9.post1
Classifier: Development Status :: 5 - Production/Stable
Classifier: Intended Audience :: Developers
Classifier: Intended Audience :: Science/Research
Classifier: License :: Other/Proprietary License
Classifier: Programming Language :: Python :: 3
Classifier: Programming Language :: Python :: 3.9
Classifier: Programming Language :: Python :: 3.10
Classifier: Programming Language :: Python :: 3.11
Classifier: Programming Language :: Python :: 3.12
Classifier: Programming Language :: Python :: 3.13
Classifier: Programming Language :: Python :: 3.14
Classifier: Programming Language :: Rust
Classifier: Topic :: Scientific/Engineering
Classifier: Topic :: Scientific/Engineering :: Artificial Intelligence
Requires-Dist: numpy>=1.20
Requires-Dist: torch>=2.0 ; extra == 'torch'
Requires-Dist: pytest ; extra == 'dev'
Requires-Dist: black ; extra == 'dev'
Requires-Dist: mypy ; extra == 'dev'
Provides-Extra: torch
Provides-Extra: dev
License-File: LICENSE.txt
Summary: High-Performance BLAS Library by OktoSeek - Tensor Core GEMM and Fused Attention
Keywords: blas,cuda,gpu,matrix,attention,transformer,deep-learning,tensor-cores
Author-email: OktoSeek AI <contact@oktoseek.com>
Maintainer-email: OktoSeek AI <contact@oktoseek.com>
License: Proprietary
Requires-Python: >=3.9
Project-URL: Homepage, https://www.oktoseek.com
Project-URL: Repository, https://github.com/oktoseek/oktoblas
Project-URL: PyPI, https://pypi.org/project/oktoblas/
